soomgogather/__init__.py
soomgogather/google/__init__.py
soomgogather/google/_googleclient.py
soomgogather/google/googleads.py
soomgogather/google/searchconsole.py
soomgogather/kakao/__init__.py
soomgogather/kakao/_kakaokeywordad.py
soomgogather/kakao/keywordreport.py
soomgogather/naver/__init__.py
soomgogather/naver/_searchad.py
soomgogather/naver/bizmoney.py
soomgogather/naver/masterreport.py
soomgogather/naver/relkwdstat.py
soomgogather/naver/statreport.py
Soomgo_gather-2.1.dist-info/LICENSE
Soomgo_gather-2.1.dist-info/METADATA
Soomgo_gather-2.1.dist-info/WHEEL
Soomgo_gather-2.1.dist-info/top_level.txt
Soomgo_gather-2.1.dist-info/RECORD
