Metadata-Version: 2.1
Name: Soomgo-gather
Version: 2.1
Home-page: https://github.com/Soomgo-Platform/soomgo-gather
Author: Brave Mobile Co., Ltd.
Author-email: platform@soomgo.com
License: MIT
Project-URL: Changelog, https://github.com/Soomgo-Platform/soomgo-gather/blob/main/CHANGELOG.md
Project-URL: Tracker, https://github.com/Soomgo-Platform/soomgo-gather/issues
Keywords: Naver,NaverSearchAD,GA,collect,data,gather,soomgo-gather,soomgo
Classifier: Development Status :: 4 - Beta
Classifier: Intended Audience :: Developers
Classifier: Programming Language :: Python
Classifier: Programming Language :: Python :: 3.6
Classifier: Programming Language :: Python :: 3.7
Classifier: Programming Language :: Python :: 3.8
Classifier: Programming Language :: Python :: 3.9
Classifier: Topic :: Software Development :: Libraries
Classifier: Topic :: Software Development :: Libraries :: Python Modules
Requires-Python: >=3.6
License-File: LICENSE
Requires-Dist: marshmallow
Requires-Dist: google-api-python-client
Requires-Dist: google-ads
Provides-Extra: test
Requires-Dist: black (>=20.8b1) ; extra == 'test'
Requires-Dist: flake8 (>=3.8.2) ; extra == 'test'
Requires-Dist: pytest ; extra == 'test'
Requires-Dist: pytest-cov ; extra == 'test'
Requires-Dist: tox ; extra == 'test'
Requires-Dist: Sphinx (>=3.2.1) ; extra == 'test'
Requires-Dist: docutils (==0.15.2) ; extra == 'test'
Requires-Dist: isort ; extra == 'test'
Requires-Dist: requests-mock ; extra == 'test'
Requires-Dist: pytest-mock ; extra == 'test'
Requires-Dist: marshmallow ; extra == 'test'
Requires-Dist: google-api-python-client ; extra == 'test'
Requires-Dist: google-ads ; extra == 'test'
